komm/__init__.py
komm/abc.py
komm/types.py
komm/_algebra/BinaryPolynomial.py
komm/_algebra/BinaryPolynomialFraction.py
komm/_algebra/FiniteBifield.py
komm/_algebra/Integers.py
komm/_algebra/__init__.py
komm/_algebra/domain.py
komm/_algebra/field.py
komm/_algebra/ring.py
komm/_channels/AWGNChannel.py
komm/_channels/BinaryErasureChannel.py
komm/_channels/BinarySymmetricChannel.py
komm/_channels/DiscreteMemorylessChannel.py
komm/_channels/ZChannel.py
komm/_channels/__init__.py
komm/_channels/base.py
komm/_constellations/APSKConstellation.py
komm/_constellations/ASKConstellation.py
komm/_constellations/Constellation.py
komm/_constellations/PAMConstellation.py
komm/_constellations/PSKConstellation.py
komm/_constellations/QAMConstellation.py
komm/_constellations/__init__.py
komm/_constellations/base.py
komm/_error_control_block/BCHCode.py
komm/_error_control_block/BlockCode.py
komm/_error_control_block/CordaroWagnerCode.py
komm/_error_control_block/CyclicCode.py
komm/_error_control_block/GolayCode.py
komm/_error_control_block/HammingCode.py
komm/_error_control_block/Lexicode.py
komm/_error_control_block/PolarCode.py
komm/_error_control_block/ReedMullerCode.py
komm/_error_control_block/RepetitionCode.py
komm/_error_control_block/SimplexCode.py
komm/_error_control_block/SingleParityCheckCode.py
komm/_error_control_block/SlepianArray.py
komm/_error_control_block/SystematicBlockCode.py
komm/_error_control_block/__init__.py
komm/_error_control_block/base.py
komm/_error_control_block/util.py
komm/_error_control_checksum/CyclicRedundancyCheck.py
komm/_error_control_checksum/__init__.py
komm/_error_control_convolutional/ConvolutionalCode.py
komm/_error_control_convolutional/HighRateConvolutionalCode.py
komm/_error_control_convolutional/LowRateConvolutionalCode.py
komm/_error_control_convolutional/TerminatedConvolutionalCode.py
komm/_error_control_convolutional/ViterbiStreamDecoder.py
komm/_error_control_convolutional/__init__.py
komm/_error_control_convolutional/base.py
komm-0.27.0.dist-info/licenses/LICENSE
komm-0.27.0.dist-info/METADATA
komm-0.27.0.dist-info/WHEEL
komm-0.27.0.dist-info/top_level.txt
komm-0.27.0.dist-info/RECORD
