Metadata-Version: 2.4
Name: komm
Version: 0.27.0
Summary: An open-source library for Python 3 providing tools for analysis and simulation of analog and digital communication systems.
Author-email: "Roberto W. Nobrega" <rwnobrega@gmail.com>
License-Expression: GPL-3.0-only
Project-URL: home, https://komm.dev/
Project-URL: repository, https://github.com/rwnobrega/komm/
Requires-Python: >=3.10
License-File: LICENSE
Requires-Dist: numpy>=2.1.1
Requires-Dist: tqdm>=4.67.0
Requires-Dist: typing-extensions>=4.12.0
Requires-Dist: typeguard>=4.4.3
Provides-Extra: lint
Requires-Dist: black==25.9.0; extra == "lint"
Requires-Dist: isort==7.0.0; extra == "lint"
Requires-Dist: flake8==7.3.0; extra == "lint"
Requires-Dist: basedpyright==1.32.1; extra == "lint"
Provides-Extra: test
Requires-Dist: pytest==8.3.3; extra == "test"
Requires-Dist: pytest-doctestplus==1.4.0; extra == "test"
Requires-Dist: pytest-repeat==0.9.3; extra == "test"
Requires-Dist: pytest-benchmark==5.1.0; extra == "test"
Requires-Dist: pytest-cov==6.0.0; extra == "test"
Provides-Extra: doc
Requires-Dist: griffe==1.7.3; extra == "doc"
Requires-Dist: griffe-inherited-docstrings==1.1.1; extra == "doc"
Requires-Dist: mkdocs==1.6.1; extra == "doc"
Requires-Dist: mkdocs-material==9.4.0; extra == "doc"
Requires-Dist: mkdocstrings==0.29.1; extra == "doc"
Requires-Dist: mkdocstrings-python==1.16.12; extra == "doc"
Requires-Dist: mkdocs-gen-files==0.5.0; extra == "doc"
Requires-Dist: mkdocs-include-markdown-plugin==6.0.4; extra == "doc"
Requires-Dist: mkdocs-literate-nav==0.6.1; extra == "doc"
Provides-Extra: debug
Requires-Dist: ipykernel>=6.28.0; extra == "debug"
Requires-Dist: matplotlib>=3.8.2; extra == "debug"
Provides-Extra: demo
Requires-Dist: streamlit==1.45.0; extra == "demo"
Requires-Dist: matplotlib==3.10.1; extra == "demo"
Dynamic: license-file
